dukascopy_python/__init__.py
dukascopy_python/instruments.py
dukascopy_python-4.0.0.dist-info/licenses/LICENSE
dukascopy_python-4.0.0.dist-info/METADATA
dukascopy_python-4.0.0.dist-info/WHEEL
dukascopy_python-4.0.0.dist-info/top_level.txt
dukascopy_python-4.0.0.dist-info/RECORD
