Metadata-Version: 2.4
Name: dukascopy_python
Version: 4.0.0
Summary: Download and stream historical price data for variety of financial instruments (Forex, Commodities and Indices) from Dukascopy Bank SA.
Author-email: Eghosa Osayande <osayandeeghosam@gmail.com>
License: MIT License
Project-URL: Homepage, https://github.com/Eghosa-Osayande/dukascopy
Keywords: tick-data,forex-data,tick-api,ticks,dukascopy
Classifier: License :: OSI Approved :: MIT License
Classifier: Programming Language :: Python
Classifier: Programming Language :: Python :: 3
Requires-Python: >=3.10
License-File: LICENSE
Requires-Dist: pandas
Requires-Dist: requests
Provides-Extra: dev
Requires-Dist: build; extra == "dev"
Requires-Dist: twine; extra == "dev"
Dynamic: license-file
